docs/conf.py
promgen/__init__.py
promgen/actions.py
promgen/admin.py
promgen/apps.py
promgen/celery.py
promgen/checks.py
promgen/context_processors.py
promgen/errors.py
promgen/filters.py
promgen/forms.py
promgen/manage.py
promgen/middleware.py
promgen/mixins.py
promgen/models.py
promgen/plugins.py
promgen/prometheus.py
promgen/proxy.py
promgen/renderers.py
promgen/rest.py
promgen/serializers.py
promgen/settings.py
promgen/shortcuts.py
promgen/signals.py
promgen/tasks.py
promgen/urls.py
promgen/util.py
promgen/validators.py
promgen/views.py
promgen/wsgi.py
promgen/discovery/__init__.py
promgen/discovery/default.py
promgen/management/__init__.py
promgen/management/commands/__init__.py
promgen/management/commands/alerts-index.py
promgen/management/commands/alerts-prune.py
promgen/management/commands/alerts-test.py
promgen/management/commands/bootstrap.py
promgen/management/commands/export-rules.py
promgen/management/commands/export-targets.py
promgen/management/commands/export-urls.py
promgen/management/commands/import-jobs.py
promgen/management/commands/import-probe.py
promgen/management/commands/register-exporter.py
promgen/management/commands/register-host.py
promgen/management/commands/register-job.py
promgen/management/commands/register-server.py
promgen/migrations/0001_squashed_0044_common-rules.py
promgen/migrations/0002_auto_20180316_0525.py
promgen/migrations/0003_alert_queue.py
promgen/migrations/0003_default-group.py
promgen/migrations/0004_merge_20180905_0247.py
promgen/migrations/0005_project_owner.py
promgen/migrations/0006_exporter_options.py
promgen/migrations/0007_message_filter.py
promgen/migrations/0008_shard_service.py
promgen/migrations/0009_blackbox-module.py
promgen/migrations/0010_app_label_migration.py
promgen/migrations/0011_notifier_counts.py
promgen/migrations/0012_validation_updates.py
promgen/migrations/0013_validation_fix.py
promgen/migrations/0014_exporter_scheme.py
promgen/migrations/0015_internal.py
promgen-0.61.0.dist-info/LICENSE
promgen-0.61.0.dist-info/METADATA
promgen-0.61.0.dist-info/NOTICE
promgen-0.61.0.dist-info/WHEEL
promgen-0.61.0.dist-info/entry_points.txt
promgen-0.61.0.dist-info/top_level.txt
promgen-0.61.0.dist-info/RECORD
