Metadata-Version: 2.1
Name: promgen
Version: 0.61.0
Author-email: LINE Corporation <dl_oss_dev@linecorp.com>
Project-URL: Source, https://github.com/line/promgen
Project-URL: Tracker, https://github.com/line/promgen/issues
Project-URL: Documentation, https://line.github.io/promgen/
Classifier: Environment :: Web Environment
Classifier: Framework :: Django
Classifier: Intended Audience :: Developers
Classifier: Operating System :: OS Independent
Classifier: Programming Language :: Python :: 3.6
Classifier: Programming Language :: Python :: 3
Classifier: Programming Language :: Python
Classifier: Topic :: Internet :: WWW/HTTP :: Dynamic Content
Classifier: Topic :: Internet :: WWW/HTTP
Requires-Python: >=3.9
License-File: LICENSE
License-File: NOTICE
Requires-Dist: Django ~=3.2
Requires-Dist: atomicwrites
Requires-Dist: celery ==4.3.0
Requires-Dist: django-environ
Requires-Dist: django-filter
Requires-Dist: djangorestframework
Requires-Dist: kombu
Requires-Dist: prometheus-client
Requires-Dist: python-dateutil
Requires-Dist: pyyaml
Requires-Dist: requests
Requires-Dist: social-auth-app-django >=2.0.0
Provides-Extra: dev
Requires-Dist: black ; extra == 'dev'
Requires-Dist: codecov ; extra == 'dev'
Requires-Dist: flake8 ; extra == 'dev'
Requires-Dist: unittest-xml-reporting ; extra == 'dev'
Provides-Extra: docs
Requires-Dist: Sphinx ; extra == 'docs'
Requires-Dist: sphinxcontrib-httpdomain ; extra == 'docs'
Provides-Extra: mysql
Requires-Dist: mysqlclient ; extra == 'mysql'
